[
    {
        "text": "@Cristiano te amo !! @Cristiano Ronaldo amo d +", 
        "created_at": "2014-07-03T00:00:44Z", 
        "id": "484486862867009536"
    }, 
    {
        "text": "@Cnyari 990 of those towards Cristiano Ronaldo.", 
        "created_at": "2014-07-03T00:27:08Z", 
        "id": "484493510348115968"
    }, 
    {
        "text": "RT @Cristiano: Acabei de fazer as minhas previs\u00f5es para o Barcelona vs. Team CR no Viva Ronaldo. E tu? - http://t.co/ZQmCmaLtYF", 
        "created_at": "2014-07-03T00:29:43Z", 
        "id": "484494159256895488"
    }, 
    {
        "text": "RT @Cristiano: Acabei de fazer as minhas previs\u00f5es para o Levante vs. Team CR no Viva Ronaldo. E tu? - http://t.co/ZQmCmaLtYF", 
        "created_at": "2014-07-03T00:34:58Z", 
        "id": "484495478285824000"
    }, 
    {
        "text": "RT @Cristiano: Can you run it like Ronaldo?  Play Cristiano Ronaldo's Footy online for FREE today!  http://t.co/T4UbPJnVzY http://t.co/wyMG\u2026", 
        "created_at": "2014-07-03T00:35:30Z", 
        "id": "484495612579033088"
    }, 
    {
        "text": "\"de onde \u00e9s?\" \"cr\" \"cr? cristiano ronaldo?\" fda-se joana", 
        "created_at": "2014-07-03T00:36:37Z", 
        "id": "484495894172409856"
    }, 
    {
        "text": "RT @Cristiano: I\u2019m launching my new underwear collection later this year! Can\u2019t wait. http://t.co/FAL12SKxQR #CR7 #ronaldo #jbs  http://t.c\u2026", 
        "created_at": "2014-07-03T00:37:05Z", 
        "id": "484496012535267329"
    }, 
    {
        "text": "RT @Cristiano: Acabei de fazer as minhas previs\u00f5es para o N. Ireland vs Portugal no Viva Ronaldo, e tu? - http://t.co/ZQmCmaLtYF", 
        "created_at": "2014-07-03T00:37:39Z", 
        "id": "484496156815134722"
    }, 
    {
        "text": "RT @Cristiano: Acabei de fazer as minhas previs\u00f5es para o Granada vs Team CR no Viva Ronaldo, e tu? - http://t.co/ZQmCmaLtYF", 
        "created_at": "2014-07-03T00:39:19Z", 
        "id": "484496574534266880"
    }, 
    {
        "text": "RT @Cristiano: Acabei de fazer as minhas previs\u00f5es para o Team CR vs Al Sadd no Viva Ronaldo, e tu? - http://t.co/ZQmCmaLtYF", 
        "created_at": "2014-07-03T00:39:27Z", 
        "id": "484496608831086592"
    }, 
    {
        "text": "@Cristiano Hey Cristiano Ronaldo i am your big fan from France and we love you! \u2661\u2661", 
        "created_at": "2014-07-03T00:53:41Z", 
        "id": "484500187755597825"
    }, 
    {
        "text": "@Cristiano   soccer ronaldo the best at your job, you're doing a great pleasure to watch you, we love you very much", 
        "created_at": "2014-07-03T00:55:19Z", 
        "id": "484500600680620032"
    }, 
    {
        "text": "@Cristiano  Christiano Ronaldo..", 
        "created_at": "2014-07-03T00:58:31Z", 
        "id": "484501405193887746"
    }, 
    {
        "text": "Mourinho e Ronaldo juntos no luxo da Gr\u00e9cia http://t.co/GskYpnru58 Ler http://t.co/Hj6M4l00Pn", 
        "created_at": "2014-07-03T00:59:04Z", 
        "id": "484501545195540480"
    }, 
    {
        "text": "@Cristiano O melhor jogador Oh como voc\u00ea \u00e9 maravilhoso Ronaldo Eu sou argelino e orgulhoso de sua &lt;3 http://t.co/3lndbwNntZ", 
        "created_at": "2014-07-03T00:59:08Z", 
        "id": "484501560186384384"
    }, 
    {
        "text": "@Cristiano ronaldo if you want to my house and gave a costume ball  I offer these fans from Surabaya Indonesia", 
        "created_at": "2014-07-03T01:08:01Z", 
        "id": "484503795125071872"
    }, 
    {
        "text": "@Cristiano Ronaldo descansa del Mundial en Mykonos http://t.co/XZ2Bo7oEpA", 
        "created_at": "2014-07-03T01:14:38Z", 
        "id": "484505461589159936"
    }, 
    {
        "text": "@Cristiano  AZ\u0130M\u0130NE HAYRANIM  (CR\u0130ST\u0130ANO RONALDO) http://t.co/O1ggGyLjqP", 
        "created_at": "2014-07-03T01:14:50Z", 
        "id": "484505514165161985"
    }, 
    {
        "text": "@Cristiano Ronaldo .. Please go home to @ManUtd .. We are very need you playing at Old Traffod again ! Go home !!!!", 
        "created_at": "2014-07-03T01:20:16Z", 
        "id": "484506877913358336"
    }, 
    {
        "text": "RT @Estadao: O que houve com Ronaldo em 98? Convuls\u00e3o \u00e9 cercada de mist\u00e9rios. Ou\u00e7a o que o seu m\u00e9dico diz: http://t.co/cS0ohvuQoA http://t.\u2026", 
        "created_at": "2014-07-03T01:25:16Z", 
        "id": "484508138906058752"
    }, 
    {
        "text": "@Cristiano &amp; his son, Ronaldo Junior, wearing matching sunnies. Super adorable! http://t.co/yqPJUNUqdU", 
        "created_at": "2014-07-03T01:33:09Z", 
        "id": "484510123746791424"
    }, 
    {
        "text": "@Cristiano HELLO Cristiano Ronaldo..Are you ok??? Because We heard that you  infected !!!Is this true??", 
        "created_at": "2014-07-03T01:34:45Z", 
        "id": "484510526278742017"
    }, 
    {
        "text": "Essa exposi\u00e7\u00e3o de cacoal ningu\u00e9m segura Ein? luan, Gabriel valim,Humberto e Ronaldo, choreeei", 
        "created_at": "2014-07-03T02:02:48Z", 
        "id": "484517585221079040"
    }, 
    {
        "text": "@Cristiano Ronaldo posso te dar um abra\u00e7o ? \u2665 Vidaaaaaaaaaaaaaa", 
        "created_at": "2014-07-03T02:20:40Z", 
        "id": "484522081091342336"
    }, 
    {
        "text": "@Cristiano RONALDO IDOL \u2665\u2665", 
        "created_at": "2014-07-03T02:58:18Z", 
        "id": "484531552022695936"
    }, 
    {
        "text": "@Cristiano I Want As Cristiano Ronaldo .... :)", 
        "created_at": "2014-07-03T03:00:50Z", 
        "id": "484532189053194241"
    }, 
    {
        "text": "Tomorrow's OJogo cover.  #Ronaldo #Izmaylov #Oliver #FCPorto http://t.co/81Usok0KwD", 
        "created_at": "2014-07-03T03:03:10Z", 
        "id": "484532775761219584"
    }, 
    {
        "text": "@Cristiano Ronaldo", 
        "created_at": "2014-07-03T03:15:52Z", 
        "id": "484535972319608833"
    }, 
    {
        "text": "@Cristiano please mr ronaldo i love you so much", 
        "created_at": "2014-07-03T03:16:55Z", 
        "id": "484536236153909248"
    }, 
    {
        "text": "@cristiano gotta love this ronaldo http://t.co/ouwS1N77mY real madrid and manchester united", 
        "created_at": "2014-07-03T03:47:30Z", 
        "id": "484543931267686400"
    }, 
    {
        "text": "@Cristiano Voc\u00ea \u00e9 meu maior \u00eddolo \u00e9 o melhor do mundo, Cristiano Ronaldo", 
        "created_at": "2014-07-03T03:54:34Z", 
        "id": "484545709593460736"
    }, 
    {
        "text": "@Cristiano Voce \u00e9 a luz que ilumina minha vida eu te amo Cristiano Ronaldo meu amorz\u00e3o voce \u00e9 muito lindo. http://t.co/LqpmdNiEPA", 
        "created_at": "2014-07-03T04:35:53Z", 
        "id": "484556107646791680"
    }, 
    {
        "text": "Namorada de Ronaldo, Irina Shayk ON FIRE http://t.co/4uftUlh8Jt", 
        "created_at": "2014-07-03T04:45:32Z", 
        "id": "484558536366895104"
    }, 
    {
        "text": "@Cristiano Ronaldo born in 1989. He live in Mediera #Portugal ReaMore http://t.co/VL7Kdb33lb\u2026", 
        "created_at": "2014-07-03T05:29:04Z", 
        "id": "484569491263614976"
    }, 
    {
        "text": "@Cristiano Ronaldo vs Manchester United - http://t.co/K7QNRukCz0  via - Real madrid 2013", 
        "created_at": "2014-07-03T05:42:09Z", 
        "id": "484572785570623488"
    }, 
    {
        "text": "@cristiano #Ronaldo #Portugal #RealMadrid #CR7 #7 by dandan8er http://t.co/NaBkr2yJ7t", 
        "created_at": "2014-07-03T06:09:28Z", 
        "id": "484579660572151808"
    }, 
    {
        "text": "@Cristiano Nike Football: Winner Stays. ft. Ronaldo, Neymar Jr., Rooney, Ibrahimovi\u0107, Iniesta &amp; more", 
        "created_at": "2014-07-03T06:14:47Z", 
        "id": "484580997665529856"
    }, 
    {
        "text": "@Cristiano Nike Football: Winner Stays. ft. Ronaldo, Neymar Jr., Rooney, Ibrahimovi\u0107, Iniesta &amp; more", 
        "created_at": "2014-07-03T06:19:52Z", 
        "id": "484582276626272256"
    }, 
    {
        "text": "@Cristiano Ronaldo :d \"@PES_ID: Pemain andalan di PES?\"", 
        "created_at": "2014-07-03T06:23:36Z", 
        "id": "484583214338424832"
    }, 
    {
        "text": "@Cristiano i very like you, spirit ronaldo", 
        "created_at": "2014-07-03T06:30:34Z", 
        "id": "484584968866127872"
    }, 
    {
        "text": "@cristiano #cristiano #ronaldo #cristianoronaldo #cr7 #sunglasses #cap #idol #best by cristianoronaldo7.7 http://t.co/9eZPRBq7EE", 
        "created_at": "2014-07-03T07:19:30Z", 
        "id": "484597284584173568"
    }, 
    {
        "text": "@Cristiano One more time the difference between #Messi and #Ronaldo... #CR7 #showrespect #WorldCup2014 http://t.co/q0OmgCCe6c", 
        "created_at": "2014-07-03T07:42:04Z", 
        "id": "484602962774605824"
    }, 
    {
        "text": "@Cristiano Ronaldo!!!We love you!!Nvm you lose the world cup..It's not your time to win..We still love you!!", 
        "created_at": "2014-07-03T07:45:47Z", 
        "id": "484603900230512642"
    }, 
    {
        "text": "@Cristiano  Hala Ronaldo!!", 
        "created_at": "2014-07-03T07:53:51Z", 
        "id": "484605928549801984"
    }, 
    {
        "text": "Benedict Cumberbatch \u00e1 voz ao document\u00e1rio sobre Cristiano Ronaldo, intitulado \"Cristiano Ronaldo:O mundo a seus p\u00e9s\" http://t.co/T6KTNCdegq", 
        "created_at": "2014-07-03T08:29:35Z", 
        "id": "484614922832060417"
    }, 
    {
        "text": "Benedict Cumberbatch d\u00e1 voz ao document\u00e1rio sobre Cristiano Ronaldo,intitulado \"Cristiano Ronaldo:O mundo a seus p\u00e9s\" http://t.co/w6zk2xmcN7", 
        "created_at": "2014-07-03T08:30:21Z", 
        "id": "484615115657191425"
    }, 
    {
        "text": "@Cristiano Cristiano Ronaldo sei un grande!! You are the number one!!", 
        "created_at": "2014-07-03T08:33:02Z", 
        "id": "484615791045005312"
    }, 
    {
        "text": "RT @iChanelBoo: as diferen\u00e7as entre o Ronaldo e o Messi... http://t.co/0WDnqQJfC5", 
        "created_at": "2014-07-03T08:45:57Z", 
        "id": "484619038270951424"
    }, 
    {
        "text": "RT @CentreTransfer: Next season potential line up:  Barcelona Front 3: Messi-Suarez-Neymar  Real Madrid Front 3: Bale-Falcao-Ronaldo", 
        "created_at": "2014-07-03T09:05:40Z", 
        "id": "484624002405920768"
    }, 
    {
        "text": "@Cristiano Ronaldo \"BEST\" http://t.co/FlwhVeBOOL", 
        "created_at": "2014-07-03T09:17:37Z", 
        "id": "484627010732699648"
    }, 
    {
        "text": "@Cristiano   cristiano ronaldo is forever  my ideal in football ....plz come to pakistan", 
        "created_at": "2014-07-03T09:50:50Z", 
        "id": "484635369787256832"
    }, 
    {
        "text": "jogador que querias ver no porto para a praoxima \u00e9poca :cristiano ronaldo kun aguero yaya toure ...\u00e9 pedir muito xd?", 
        "created_at": "2014-07-03T10:01:46Z", 
        "id": "484638118277316608"
    }, 
    {
        "text": "@Cristiano {}\"@infoFAKTA: Pesepak bola, Cristiano Ronaldo, pernah mnjdi donor sumsum tulang belakang untuk seorang anak penderita leukimia.\"", 
        "created_at": "2014-07-03T10:30:46Z", 
        "id": "484645419213807617"
    }, 
    {
        "text": "@cristiano this just happened \ud83d\ude31\ud83d\ude31\u263a\ufe0f\u263a\ufe0f\ud83d\ude0d\ud83d\ude0d i hardly go on fifa anymore \ud83d\ude0d\ud83d\ude0d\ud83d\ude0d\ud83d\ude0d #fifa14 #yesss #ronaldo #cr7 #fave #fifa ... http://t.co/FBT5aLGFW5", 
        "created_at": "2014-07-03T10:34:19Z", 
        "id": "484646312034725889"
    }, 
    {
        "text": "Arg\u00e9lia vai doar os pr\u00e9mios monet\u00e1rios do Mundial ao povo de Gaza. O Ronaldo vai construir mais uma ala do Museu Cristiano Ronaldo. #egos", 
        "created_at": "2014-07-03T10:39:53Z", 
        "id": "484647713376841728"
    }, 
    {
        "text": "RT @ojewhunter: PREACH @imascoldasice Aquele gajo tem mais amor \u00e0 camisola que usa e a equipa que representa do que o pr\u00f3prio ronaldo dont \u2026", 
        "created_at": "2014-07-03T10:47:27Z", 
        "id": "484649615070101504"
    }, 
    {
        "text": "@ojewhunter @lorddospeasants @imascoldasice Ronaldo e Quaresma juntos rebentava TUDO!", 
        "created_at": "2014-07-03T10:47:58Z", 
        "id": "484649745231937536"
    }, 
    {
        "text": "Tutto su Cristiano Ronaldo in un libro - Calcio - Sportmediaset http://t.co/3wTbjabpYb via @Sport_Mediaset", 
        "created_at": "2014-07-03T10:58:05Z", 
        "id": "484652291580903425"
    }, 
    {
        "text": "Tutto su Cristiano Ronaldo in un libro - Calcio - Sportmediaset via @Sport_Mediaset", 
        "created_at": "2014-07-03T10:59:14Z", 
        "id": "484652581457641473"
    }, 
    {
        "text": "@cristiano gotta love this ronaldo http://t.co/8k5J63iqI4 real madrid and manchester united", 
        "created_at": "2014-07-03T11:17:33Z", 
        "id": "484657192927125505"
    }, 
    {
        "text": "RT @FCPortoWorld: Tomorrow's OJogo cover.  #Ronaldo #Izmaylov #Oliver #FCPorto http://t.co/81Usok0KwD", 
        "created_at": "2014-07-03T11:18:20Z", 
        "id": "484657386821808129"
    }, 
    {
        "text": "Cristiano Ronaldo: Passa f\u00e9rias sem Irina http://t.co/r0W6cUa7bo", 
        "created_at": "2014-07-03T11:24:09Z", 
        "id": "484658851224883202"
    }, 
    {
        "text": "@Cristiano Hi Ronaldo", 
        "created_at": "2014-07-03T11:24:53Z", 
        "id": "484659037716627457"
    }, 
    {
        "text": "Ryan Gauld follows in footsteps of Ronaldo and Figo at Sporting Lisbon http://t.co/8UioWBgpfn", 
        "created_at": "2014-07-03T11:28:12Z", 
        "id": "484659870168125440"
    }, 
    {
        "text": "Este Fen\u00f3meno, Ronaldo Fen\u00f3meno, est\u00e1 de facto a ficar a dever pouco \u00e0 obesidade. http://t.co/bSjBknZZPK", 
        "created_at": "2014-07-03T11:36:52Z", 
        "id": "484662052565581825"
    }, 
    {
        "text": "@Cristiano Really Ronaldo?", 
        "created_at": "2014-07-03T11:48:52Z", 
        "id": "484665071147048960"
    }, 
    {
        "text": "Ronaldo, tens uma floresta para salvar! http://t.co/UxbuUZztuX", 
        "created_at": "2014-07-03T11:49:37Z", 
        "id": "484665260775714816"
    }, 
    {
        "text": "RT @rpOliveira: Este Fen\u00f3meno, Ronaldo Fen\u00f3meno, est\u00e1 de facto a ficar a dever pouco \u00e0 obesidade. http://t.co/bSjBknZZPK", 
        "created_at": "2014-07-03T11:52:07Z", 
        "id": "484665891167420416"
    }, 
    {
        "text": "Cristiano Ronaldo surfing: http://t.co/iFcw4VZywR #video", 
        "created_at": "2014-07-03T11:55:48Z", 
        "id": "484666814967066624"
    }, 
    {
        "text": "@bancadadeleao a n\u00edvel de clubes, sim. A liga\u00e7\u00e3o Ronaldo/FPF parece-me para durar.", 
        "created_at": "2014-07-03T11:59:06Z", 
        "id": "484667648417234945"
    }, 
    {
        "text": "@Cristiano Ronaldo est\u00e1 em uma Ilha Grega chamada \"Mykonos\" curtindo suas f\u00e9rias. Segundo boatos, o gajo teria chegado domingo por l\u00e1.", 
        "created_at": "2014-07-03T12:09:58Z", 
        "id": "484670382981783552"
    }, 
    {
        "text": "@Cristiano Ronaldo &amp; Cristiano Jr. Momento pai e filho \"fam\u00edlia\" http://t.co/czDFF7Nl0w", 
        "created_at": "2014-07-03T12:12:48Z", 
        "id": "484671093299744768"
    }, 
    {
        "text": "Abre os olhos Paulo Bento!!! ---&gt;&gt;Actriz porno \u00c9rica Fontes \u00e9 mais procurada no Google do que Cristiano Ronaldo http://t.co/pEpkZ0fQtv", 
        "created_at": "2014-07-03T12:15:24Z", 
        "id": "484671747560448000"
    }, 
    {
        "text": "O Ronaldo e o Mourinho foram de f\u00e9rias para a Gr\u00e9cia na mesma altura sem saberem ahahahahahaha", 
        "created_at": "2014-07-03T12:17:38Z", 
        "id": "484672312181264384"
    }, 
    {
        "text": "[Diario de Noticias] Mourinho e Ronaldo de f\u00e9rias rodeados de luxo http://t.co/FHqDHx7y84", 
        "created_at": "2014-07-03T12:20:53Z", 
        "id": "484673130984513537"
    }, 
    {
        "text": "RT @FootballFunnys: Next season potential line up:  Barcelona Front 3: Messi-Suarez-Neymar  Real Madrid Front 3: Bale-Falcao-Ronaldo", 
        "created_at": "2014-07-03T12:30:44Z", 
        "id": "484675608593858560"
    }, 
    {
        "text": "@Cristiano mon h\u00e9ro Ronaldo.1 2 3 Viva l Alg\u00e9rie", 
        "created_at": "2014-07-03T12:36:37Z", 
        "id": "484677087257960449"
    }, 
    {
        "text": "@Cristiano Viva Ronaldo", 
        "created_at": "2014-07-03T12:53:16Z", 
        "id": "484681277162151937"
    }, 
    {
        "text": "@Cristiano Please Tweet This Ronaldo ,,My Video For You - https://t.co/DUQjxqB7rT", 
        "created_at": "2014-07-03T12:53:17Z", 
        "id": "484681281960026112"
    }, 
    {
        "text": "@Cristiano I LOVE YOU CRISTIANO RONALDO", 
        "created_at": "2014-07-03T12:53:26Z", 
        "id": "484681319339667459"
    }, 
    {
        "text": "@Cristiano Ronaldo on holiday \ud83d\ude0e\u2600\ufe0f http://t.co/5I0S0J9cLz", 
        "created_at": "2014-07-03T12:54:04Z", 
        "id": "484681479860269056"
    }, 
    {
        "text": "@Cristiano Ronaldo I love you I always have please follow me!!", 
        "created_at": "2014-07-03T12:54:05Z", 
        "id": "484681485170270208"
    }, 
    {
        "text": "@Cristiano You did great comandante Ronaldo", 
        "created_at": "2014-07-03T12:54:06Z", 
        "id": "484681490597683200"
    }, 
    {
        "text": "@Cristiano enjoy your holiday! #staysafe Cristiano Hero Ronaldo", 
        "created_at": "2014-07-03T12:54:26Z", 
        "id": "484681570931195905"
    }, 
    {
        "text": "@Cristiano s\u00edgueme \u00eddolo por favor ! Apoyo CR7 desde Colombia !   CRISTIANO RONALDO COLOMBIA", 
        "created_at": "2014-07-03T12:54:41Z", 
        "id": "484681636798550017"
    }, 
    {
        "text": "@Cristiano miss you a lot. ..Ronaldo. ..", 
        "created_at": "2014-07-03T12:54:49Z", 
        "id": "484681668909744128"
    }, 
    {
        "text": "@Cristiano hy ronaldo", 
        "created_at": "2014-07-03T12:55:21Z", 
        "id": "484681801198075904"
    }, 
    {
        "text": "@Cristiano hi ronaldo dont worry in the next world cup portugal will win", 
        "created_at": "2014-07-03T12:55:45Z", 
        "id": "484681905095208960"
    }, 
    {
        "text": "@Cristiano CAREFULLY :) RONALDO :) WE MISS U", 
        "created_at": "2014-07-03T12:55:57Z", 
        "id": "484681955179778048"
    }, 
    {
        "text": "@Cristiano aferin ronaldo sen \u00e7ok iyisin", 
        "created_at": "2014-07-03T12:55:58Z", 
        "id": "484681959395041280"
    }, 
    {
        "text": "@cristiano Ronaldo dis oke", 
        "created_at": "2014-07-03T12:56:08Z", 
        "id": "484682000218193920"
    }, 
    {
        "text": "@cristiano very nice cristiano ronaldo", 
        "created_at": "2014-07-03T12:56:11Z", 
        "id": "484682013757038593"
    }, 
    {
        "text": "@Cristiano \"@Madrid_Sukabumi Lebih milih Cristiano Ronaldo atau Jese Rodriguez? #MisukASK", 
        "created_at": "2014-07-03T12:56:58Z", 
        "id": "484682210084007936"
    }, 
    {
        "text": "@Cristiano ronaldo u are so handsome!!!!", 
        "created_at": "2014-07-03T12:59:15Z", 
        "id": "484682784435208192"
    }, 
    {
        "text": "@Cristiano Ronaldo planea tener su propia cadena de hoteles http://t.co/uNxsZm2t17", 
        "created_at": "2014-07-03T13:00:18Z", 
        "id": "484683047883661313"
    }, 
    {
        "text": "@Cristiano is these the real Ronaldo or some one on his behalf?", 
        "created_at": "2014-07-03T13:03:44Z", 
        "id": "484683913236054016"
    }, 
    {
        "text": "@Cristiano brave ronaldo I real appreciate you", 
        "created_at": "2014-07-03T13:05:28Z", 
        "id": "484684347833073665"
    }, 
    {
        "text": "@Cristiano e ai Ronaldo... Quanto t\u00e1 custando a escova permanente ai em Portugal....  Rs...", 
        "created_at": "2014-07-03T13:06:39Z", 
        "id": "484684645024673792"
    }, 
    {
        "text": "@Cristiano great brother ronaldo", 
        "created_at": "2014-07-03T13:12:59Z", 
        "id": "484686239602208769"
    }, 
    {
        "text": "@Cristiano FOLLOW ME PLEASE RONALDO U AR MY IDOL", 
        "created_at": "2014-07-03T13:13:00Z", 
        "id": "484686244216328192"
    }, 
    {
        "text": "@Cristiano PLEASE RONALDO IF U SEE THIS TWEET FOLLOW ME", 
        "created_at": "2014-07-03T13:14:25Z", 
        "id": "484686599528415232"
    }, 
    {
        "text": "@Cristiano love u Ronaldo &lt;3", 
        "created_at": "2014-07-03T13:14:31Z", 
        "id": "484686627277910016"
    }, 
    {
        "text": "@cristiano Ronaldo and son LoL #likefatherlikeson http://t.co/7w3Bfedo4R", 
        "created_at": "2014-07-03T13:15:45Z", 
        "id": "484686938902106112"
    }, 
    {
        "text": "@Cristiano PLEASEEEEEE PLEASEEEEEEE RONALDO  IF U SEE THIS TWEEET #FOLLOWWWW #MEEEEEEEEEEEEEEEEE", 
        "created_at": "2014-07-03T13:16:45Z", 
        "id": "484687189625016320"
    }, 
    {
        "text": "@Cristiano any time and we hope to see a better and stronger Ronaldo next season.", 
        "created_at": "2014-07-03T13:19:35Z", 
        "id": "484687902077911041"
    }, 
    {
        "text": "@Cristiano   hello  ronaldo  nice  to  meet  u", 
        "created_at": "2014-07-03T13:20:02Z", 
        "id": "484688013985710081"
    }, 
    {
        "text": "@Cristiano fuk u ronaldo", 
        "created_at": "2014-07-03T13:20:57Z", 
        "id": "484688245649727489"
    }, 
    {
        "text": "ronaldo and his vacation time haircuts...... lol", 
        "created_at": "2014-07-03T13:22:54Z", 
        "id": "484688735049908224"
    }, 
    {
        "text": "@Cristiano it's our duty as ur fans 2 support u always CR7 \u2665 viva Ronaldo \u2661 Vamos Cris \u2661", 
        "created_at": "2014-07-03T13:25:35Z", 
        "id": "484689410986762240"
    }, 
    {
        "text": "@Cristiano Hi Ronaldo, are u planning to travel to Singapore soon? http://t.co/LwaHDIqfH5", 
        "created_at": "2014-07-03T13:30:40Z", 
        "id": "484690692761866240"
    }, 
    {
        "text": "@Cristiano Cristiano Ronaldo you are a super football player", 
        "created_at": "2014-07-03T13:30:54Z", 
        "id": "484690751658684416"
    }, 
    {
        "text": "#savethetrees - #savetheforest - #greenpeace - #trees - #ronaldo - \"Ronaldo, corta l\u00e1 o cabelo! E salva a... http://t.co/mJfl2Df0yV", 
        "created_at": "2014-07-03T13:38:56Z", 
        "id": "484692770565931008"
    }, 
    {
        "text": "Faltava apenas o Figo e o Ronaldo. Para a pr\u00f3xima talvez ponham uma foto do Moutinho e do Quaresma #LT", 
        "created_at": "2014-07-03T13:46:01Z", 
        "id": "484694554910920705"
    }, 
    {
        "text": "@Cristiano Ronaldo, I love you and I want to become like you in the future as you can see in the picture its me :) !!", 
        "created_at": "2014-07-03T13:50:26Z", 
        "id": "484695667034447873"
    }, 
    {
        "text": "@Cristiano &lt;3 &lt;3 &lt;3 Cristiano Ronaldo :-)", 
        "created_at": "2014-07-03T13:50:34Z", 
        "id": "484695697409970176"
    }, 
    {
        "text": "@Cristiano Ronaldo, I love you and I want to become like you in the future as you can see in the picture its me :) ! http://t.co/3p702niCOM", 
        "created_at": "2014-07-03T13:51:18Z", 
        "id": "484695881795776512"
    }, 
    {
        "text": "@Cristiano Ronaldo, I love you and I want to become like you in the future as you can see in the picture its me :) !! http://t.co/PMpHHjUI8y", 
        "created_at": "2014-07-03T13:52:22Z", 
        "id": "484696150814244864"
    }, 
    {
        "text": "@Cristiano ronaldo my brother loves u", 
        "created_at": "2014-07-03T13:57:00Z", 
        "id": "484697317002739713"
    }, 
    {
        "text": "@Cristiano  Viva Ronaldo", 
        "created_at": "2014-07-03T14:01:02Z", 
        "id": "484698332804026368"
    }, 
    {
        "text": "@Cristiano sos el mejor ronaldo", 
        "created_at": "2014-07-03T14:03:49Z", 
        "id": "484699033810657280"
    }, 
    {
        "text": "@Cristiano please ronaldo i bag you for the second time check me via anyilangile2nyi@gmail.com", 
        "created_at": "2014-07-03T14:04:32Z", 
        "id": "484699214577139712"
    }, 
    {
        "text": "@Cristiano Ronaldo #NA http://t.co/DA1ch8yU8a", 
        "created_at": "2014-07-03T14:07:44Z", 
        "id": "484700017299423233"
    }, 
    {
        "text": "[DNoticias] Cristiano Ronaldo oficialmente de f\u00e9rias 'brinca' \u00e0 bola com o sol http://t.co/31NvyS9wWj", 
        "created_at": "2014-07-03T14:07:53Z", 
        "id": "484700055178194944"
    }, 
    {
        "text": "@Alex__rk Lol Nah,I think ppl do way too much about him and he's far from being on Ronaldo/Romario's level.", 
        "created_at": "2014-07-03T14:09:47Z", 
        "id": "484700533232779264"
    }, 
    {
        "text": "@Cristiano you really cristiano ronaldo ??", 
        "created_at": "2014-07-03T14:10:41Z", 
        "id": "484700761331609600"
    }, 
    {
        "text": "@Cristiano @theCRTeam @realmadrid ronaldo", 
        "created_at": "2014-07-03T14:12:17Z", 
        "id": "484701163716366336"
    }, 
    {
        "text": "@Lu_May_ he's still young though got a lot to learn.... his talent isn't as natural as Ronaldo and em but he's good... and will get better", 
        "created_at": "2014-07-03T14:18:52Z", 
        "id": "484702822504857600"
    }, 
    {
        "text": "@Cristiano  viva ronaldo", 
        "created_at": "2014-07-03T14:19:17Z", 
        "id": "484702925256941568"
    }, 
    {
        "text": "@Cristiano hey ronaldo i am from korea.i want to soccer player. I want for scout at spain. Help me.. Please", 
        "created_at": "2014-07-03T14:20:58Z", 
        "id": "484703349548515328"
    }, 
    {
        "text": "@Pinilla84 avancemos... quero o teu coment\u00e1rio ao facto do Ronaldo cagar na irina e ir para Mykonos com os amigos @JG1904", 
        "created_at": "2014-07-03T14:22:48Z", 
        "id": "484703809651105793"
    }, 
    {
        "text": "@Cristiano hi ronaldo im a big fan hope to be a soccer player when im big just like you", 
        "created_at": "2014-07-03T14:23:32Z", 
        "id": "484703995215491072"
    }, 
    {
        "text": "@Cristiano Ronaldo you super", 
        "created_at": "2014-07-03T14:30:25Z", 
        "id": "484705727437496320"
    }, 
    {
        "text": "@Cristiano Viva Ronaldo", 
        "created_at": "2014-07-03T14:41:58Z", 
        "id": "484708634639626240"
    }, 
    {
        "text": "Ronaldo enfrenta vereadores \u2018rebeldes\u2019 e brigas no 1\u00ba escal\u00e3o http://t.co/zZOoaqkAvC http://t.co/s6BKD1R5Rz", 
        "created_at": "2014-07-03T14:43:09Z", 
        "id": "484708930036060160"
    }, 
    {
        "text": "@Cristiano Ronaldo. http://t.co/nZ1rMlragj\"", 
        "created_at": "2014-07-03T14:45:16Z", 
        "id": "484709465988419584"
    }, 
    {
        "text": "#fame #famosos Cristiano Ronaldo de f\u00e9rias sem Irina Shayk: O internacional portugu\u00eas est\u00e1 em Mykonos, na Gr\u00e9c... http://t.co/kJ5uLAjYOk", 
        "created_at": "2014-07-03T14:58:16Z", 
        "id": "484712737939808256"
    }, 
    {
        "text": "@Cristiano kkkkkkkkkkkkkkkkbom dia ronaldo", 
        "created_at": "2014-07-03T14:59:02Z", 
        "id": "484712929737310208"
    }, 
    {
        "text": "\u00abObrigada pelo vosso apoio durante toda a temporada\u00bb, Cristiano Ronaldo http://t.co/1A448rMcwz", 
        "created_at": "2014-07-03T15:05:58Z", 
        "id": "484714675649921024"
    }, 
    {
        "text": "O Cristiano Ronaldo est\u00e1 de f\u00e9rias em Mykonos e decidiu brincar com o sol.   Vamos tentar adivinhar quantas fotos... http://t.co/WLuR0iIIfn", 
        "created_at": "2014-07-03T15:16:33Z", 
        "id": "484717337799819264"
    }, 
    {
        "text": "@Cristiano Spain's coach says Ronaldo can not dribbling like Messi and Neymar strong words", 
        "created_at": "2014-07-03T15:22:59Z", 
        "id": "484718954477133824"
    }, 
    {
        "text": "@Cristiano : Cristiano Ronaldo with holiday.\u2764You are number1 in my heart.\ud83d\udc98Love you.\ud83d\udc9e http://t.co/OwhM0Ynv7G", 
        "created_at": "2014-07-03T15:41:27Z", 
        "id": "484723605003976705"
    }, 
    {
        "text": "RT @TransferSources: Next season potential line up:  Barcelona Front 3: Messi-Suarez-Neymar  Real Madrid Front 3: Bale-Falcao-Ronaldo", 
        "created_at": "2014-07-03T15:43:55Z", 
        "id": "484724224800882689"
    }, 
    {
        "text": "@Cristiano ronaldo 2 days after my birthday", 
        "created_at": "2014-07-03T15:44:28Z", 
        "id": "484724361073786880"
    }, 
    {
        "text": "RT @antitikitaka: Vincent Del Bosque: \"Ronaldo is less creative than Neymar and Messi.\" Dear lord, it was 11 years ago, let it go!!!! PS 5-\u2026", 
        "created_at": "2014-07-03T15:47:31Z", 
        "id": "484725128727916544"
    }, 
    {
        "text": "RT @antitikitaka: Vincent Del Bosque: \"Ronaldo is less creative than Neymar and Messi.\" Dear lord, it was 11 years ago, let it go!!!! PS 5-\u2026", 
        "created_at": "2014-07-03T15:52:37Z", 
        "id": "484726413824909312"
    }, 
    {
        "text": "@Cristiano ronaldo your for life ilove you ronaldo", 
        "created_at": "2014-07-03T15:53:53Z", 
        "id": "484726732021174272"
    }, 
    {
        "text": "@Cristiano Cristiano Ronaldo Best Player You're My Favorite Sin you Good Luck Team You Da One Tweet Share For me in. ...", 
        "created_at": "2014-07-03T15:57:19Z", 
        "id": "484727595179974656"
    }, 
    {
        "text": "RT @antitikitaka: Vincent Del Bosque: \"Ronaldo is less creative than Neymar and Messi.\" Dear lord, it was 11 years ago, let it go!!!! PS 5-\u2026", 
        "created_at": "2014-07-03T15:58:31Z", 
        "id": "484727897760862208"
    }, 
    {
        "text": "@Cristiano Viva Ronaldo!!!!", 
        "created_at": "2014-07-03T16:02:52Z", 
        "id": "484728993988349952"
    }, 
    {
        "text": "@Cristiano Ronaldo dos Santos Aveiro  iyiki vars\u0131n  :)  :)  :)  @Fenerbahce", 
        "created_at": "2014-07-03T16:10:46Z", 
        "id": "484730980692156416"
    }, 
    {
        "text": "@Cristiano Ronaldo. http://t.co/QfT20V2y6z", 
        "created_at": "2014-07-03T16:12:21Z", 
        "id": "484731378580602880"
    }, 
    {
        "text": "@Cristiano Viva Ronaldo!  \u2665", 
        "created_at": "2014-07-03T16:15:28Z", 
        "id": "484732163896516609"
    }, 
    {
        "text": "@Cristiano hello I ronaldo ... \" you speak of, I am proud to be a good match, barcelona, real madrid's a fight  can you fix", 
        "created_at": "2014-07-03T16:21:59Z", 
        "id": "484733804465369090"
    }, 
    {
        "text": "Ronaldo enfrenta vereadores 'rebeldes' e brigas no 1\u00ba escal\u00e3o http://t.co/2zGcN5KZkd", 
        "created_at": "2014-07-03T16:23:35Z", 
        "id": "484734207324065792"
    }, 
    {
        "text": "@Cristiano hey ronaldo if ur able to check this out, made a youtube speedpainting with u &amp; others for the WC :D https://t.co/OG94Y5FBf8", 
        "created_at": "2014-07-03T16:30:10Z", 
        "id": "484735865542172672"
    }, 
    {
        "text": "@Cristiano Ronaldo could have scored many goals for portugal in the #WC  if his team wasn't so selfish now that I look back at the matches", 
        "created_at": "2014-07-03T16:43:28Z", 
        "id": "484739211195858944"
    }, 
    {
        "text": "Gostei de um v\u00eddeo do @YouTube http://t.co/IuqMwrnwLb Cristiano Ronaldo Mostra sua Casa em Madri", 
        "created_at": "2014-07-03T16:46:39Z", 
        "id": "484740013611962369"
    }, 
    {
        "text": "@luismateus Di Maria final de \u00e9poca espectacular. Sempre a cobrir Ronaldo. (pois! 50 por Luiz.) Jorge Mendes \u00e9 um jogador de xadrez terrivel", 
        "created_at": "2014-07-03T16:49:28Z", 
        "id": "484740720075735040"
    }, 
    {
        "text": "Ronaldo enfrenta vereadores 'rebeldes' e brigas no 1\u00ba escal\u00e3o http://t.co/nPbtC4N0DU", 
        "created_at": "2014-07-03T16:54:29Z", 
        "id": "484741983630819328"
    }, 
    {
        "text": "RT @blogdafeira: Ronaldo enfrenta vereadores 'rebeldes' e brigas no 1\u00ba escal\u00e3o http://t.co/nPbtC4N0DU", 
        "created_at": "2014-07-03T16:59:35Z", 
        "id": "484743267133960192"
    }, 
    {
        "text": "no videoclip da musica do mundial de portugal s\u00f3 aparece mm o ronaldo e depois numa parte os portugueses... s\u00f3 temos 1 jogador mm", 
        "created_at": "2014-07-03T17:03:13Z", 
        "id": "484744180821139456"
    }, 
    {
        "text": "@Cristiano saludos desde Colombia \u00eddolo ! Mandando un saludo por favor ! O s\u00edguenos   CRISTIANO RONALDO FANS COLOMBIA", 
        "created_at": "2014-07-03T17:03:26Z", 
        "id": "484744236454395904"
    }, 
    {
        "text": "@Cristiano ronaldo is perfect", 
        "created_at": "2014-07-03T17:03:55Z", 
        "id": "484744358609309697"
    }, 
    {
        "text": "@Cristiano Ronaldo thy appearance less so good on the World Cup 2014, what ronaldo??", 
        "created_at": "2014-07-03T17:05:09Z", 
        "id": "484744665669705728"
    }, 
    {
        "text": "@Cristiano ronaldo you are my everything! love you\u2764\ufe0f", 
        "created_at": "2014-07-03T17:05:25Z", 
        "id": "484744736209506304"
    }, 
    {
        "text": "@Cristiano stay blessed Ronaldo lots of love \u2665\u2665\u2665\u2665\u2665", 
        "created_at": "2014-07-03T17:05:50Z", 
        "id": "484744839439728640"
    }, 
    {
        "text": "@Cristiano  Hello Ronaldo!&lt;33 Big love from Denmark!", 
        "created_at": "2014-07-03T17:06:38Z", 
        "id": "484745042205343744"
    }, 
    {
        "text": "Gostei de um v\u00eddeo do @YouTube http://t.co/D9xNU8rRrq Cristiano Ronaldo - WORLD CUP 2014 \u25ba Hero of Portugal | USA vs Portugal", 
        "created_at": "2014-07-03T17:08:14Z", 
        "id": "484745444455505920"
    }, 
    {
        "text": "@cristiano i miss you in fifa worldcup ronaldo anyway all the best ready for the next cup", 
        "created_at": "2014-07-03T17:08:18Z", 
        "id": "484745459018518529"
    }, 
    {
        "text": "RT @marciiiasilva: Porque Portugal n\u00e3o \u00e9 s\u00f3 Ronaldo! LOL RT Erica Fontes, 21 anos, \u00e9 a melhor actriz porno estrangeira | P3 http://t.co/OD7\u2026", 
        "created_at": "2014-07-03T17:09:03Z", 
        "id": "484745649364434944"
    }, 
    {
        "text": "@Cristiano Ronaldo .. Please, I want to be reassured injury from my friend .. \u2764 \ufe0f", 
        "created_at": "2014-07-03T17:09:57Z", 
        "id": "484745876015816704"
    }, 
    {
        "text": "@Cristiano Ronaldo\u2665", 
        "created_at": "2014-07-03T17:11:31Z", 
        "id": "484746268661395458"
    }, 
    {
        "text": "Ronaldo quer abrir rede de hot\u00e9is com a marca CR7.  http://t.co/Stzrm6xgut", 
        "created_at": "2014-07-03T17:14:12Z", 
        "id": "484746944439656448"
    }, 
    {
        "text": "@Cristiano Hello Don Ronaldo. I love your game is nice and I hope to visit Algeria", 
        "created_at": "2014-07-03T17:14:37Z", 
        "id": "484747050240978944"
    }, 
    {
        "text": "@Cristiano Hi Ronaldo ( BEST PLAYER ALL TIME) ,can you send me your photo please , I LOVE YOU, BEST WISHES.", 
        "created_at": "2014-07-03T17:15:36Z", 
        "id": "484747298325688320"
    }, 
    {
        "text": "@Cristiano this not a good video ronaldo I can do this !!", 
        "created_at": "2014-07-03T17:18:41Z", 
        "id": "484748074829766656"
    }, 
    {
        "text": "# Cristiano Ronaldo faz f\u00e9rias na Gr\u00e9cia http://t.co/lF7fORKz5I  em http://t.co/VGvFS4lnWd", 
        "created_at": "2014-07-03T17:26:20Z", 
        "id": "484749998161010688"
    }, 
    {
        "text": "RT @ojogo: # Cristiano Ronaldo faz f\u00e9rias na Gr\u00e9cia http://t.co/lF7fORKz5I  em http://t.co/VGvFS4lnWd", 
        "created_at": "2014-07-03T17:29:42Z", 
        "id": "484750843996938242"
    }, 
    {
        "text": "[O Jogo] Cristiano Ronaldo faz f\u00e9rias na Gr\u00e9cia http://t.co/dw2bgi6WIn #desporto", 
        "created_at": "2014-07-03T17:32:14Z", 
        "id": "484751481971564544"
    }, 
    {
        "text": "@Cristiano holla cristiano ronaldo , bue\u00f1os dias", 
        "created_at": "2014-07-03T17:32:43Z", 
        "id": "484751604654944256"
    }, 
    {
        "text": "@Cristiano viva ronaldo", 
        "created_at": "2014-07-03T17:41:01Z", 
        "id": "484753692776607745"
    }, 
    {
        "text": "@Cristiano Ronaldo akan absen di UEFA Super Cup(vs Sevilla) sampai cidera-nya benar-benar pulih [@JugoneslaSexta]", 
        "created_at": "2014-07-03T17:42:07Z", 
        "id": "484753970208845825"
    }, 
    {
        "text": "@Cristiano @david_alexi I love you RONALDO", 
        "created_at": "2014-07-03T17:45:41Z", 
        "id": "484754867509280768"
    }, 
    {
        "text": "@Cristiano hi ronaldo", 
        "created_at": "2014-07-03T17:46:36Z", 
        "id": "484755099667804161"
    }, 
    {
        "text": "Hahahaha um mi\u00fado veio-me perguntar quem jogava melhor: o Ribery ou o Ozil! Eu disse o Ozil! Depois perguntou: Ronaldo ou Ozil! Adorei \ud83d\ude02", 
        "created_at": "2014-07-03T17:47:49Z", 
        "id": "484755403897860096"
    }, 
    {
        "text": "@Cristiano Ronaldo @luis16suarez #KarinBenzema independientemente del rendimiento y de los resultados SIGUEN SIENDO MIS CONSENTIDOS!!!", 
        "created_at": "2014-07-03T18:03:38Z", 
        "id": "484759385730977793"
    }, 
    {
        "text": "@cristiano Nike Commercial \u00a4 Rooney \u00a4 Tevez \u00a4 Ibra \u00a4 Ronaldo \u00a4 Ronaldinho &amp; Other S...: http://t.co/DrsuWfmetU @YouTube arac\u0131l\u0131\u011f\u0131yla", 
        "created_at": "2014-07-03T18:04:46Z", 
        "id": "484759669701767168"
    }, 
    {
        "text": "@Cristiano Ronaldo sou seu maior fan vce demais cara,fico triste pq vc saiu da copa mas vc e o cara...#ForcaCris", 
        "created_at": "2014-07-03T18:11:52Z", 
        "id": "484761456836349952"
    }, 
    {
        "text": "Cristiano Ronaldo: \"Starting the holidays playing with the sun in this landscape. Thank you for the  http://t.co/xQ6Zvn6MKg", 
        "created_at": "2014-07-03T18:22:44Z", 
        "id": "484764192172687360"
    }, 
    {
        "text": "@Cristiano this is the new twitter of footballer Cristiano Ronaldo make sure to follow.", 
        "created_at": "2014-07-03T18:25:41Z", 
        "id": "484764934753222656"
    }, 
    {
        "text": "@Cristiano HELLO Cristiano Ronaldo..Are you ok??? Because We heard that you  infected !!!Is this true??", 
        "created_at": "2014-07-03T18:26:08Z", 
        "id": "484765046825037825"
    }, 
    {
        "text": "@Cristiano Ronaldo voc\u00ea \u00e9 demais !!!", 
        "created_at": "2014-07-03T18:27:55Z", 
        "id": "484765497221980160"
    }, 
    {
        "text": "Adri Amaral, Ronaldo Henn, Daniel Bittencourt, Guilherme Caon, Eloisa Klein, Luciana Carvalho\u2026 http://t.co/sPyXkBE8jw", 
        "created_at": "2014-07-03T18:28:10Z", 
        "id": "484765561365479424"
    }, 
    {
        "text": "@Cristiano  dear Ronaldo best wishes for you", 
        "created_at": "2014-07-03T18:29:20Z", 
        "id": "484765852475342848"
    }, 
    {
        "text": "Ronaldo enfrenta vereadores 'rebeldes' e brigas no 1\u00ba escal\u00e3o http://t.co/DkLHlLBYRD", 
        "created_at": "2014-07-03T18:33:45Z", 
        "id": "484766964452458498"
    }, 
    {
        "text": "@Cristiano follow me ronaldo", 
        "created_at": "2014-07-03T18:36:37Z", 
        "id": "484767687134810112"
    }, 
    {
        "text": "RT @blogdafeira: Ronaldo enfrenta vereadores 'rebeldes' e brigas no 1\u00ba escal\u00e3o http://t.co/DkLHlLBYRD", 
        "created_at": "2014-07-03T18:38:37Z", 
        "id": "484768187427602433"
    }, 
    {
        "text": "@Cristiano Ronaldo vs MANCHESTER UNITED - http://t.co/jf530iqhUM via - Real madrid 2013", 
        "created_at": "2014-07-03T18:46:40Z", 
        "id": "484770216228839424"
    }, 
    {
        "text": "Como assim o Ronaldo vai lan\u00e7ar uma rede de hot\u00e9is? I mean, se eu fosse rica como ele fazia o mesmo, mas still...", 
        "created_at": "2014-07-03T19:01:36Z", 
        "id": "484773971712561152"
    }, 
    {
        "text": "@Cristiano Hey Ronaldo I'm Hamza  from Morocco you are my idol please can you say ' Ramadan Mubarak '", 
        "created_at": "2014-07-03T19:07:54Z", 
        "id": "484775556471590912"
    }, 
    {
        "text": "@joaomiranda Deixem de pagar ao Ronaldo e \u00e0 D.... como \u00e9 que se chama a mulher?... D\u00edvida?", 
        "created_at": "2014-07-03T19:12:00Z", 
        "id": "484776590673727490"
    }, 
    {
        "text": "@Cristiano showboating against Arsenal.. Mesmerizing skills.. Ohhhh i miss Ronnie... #vine #skills #ronaldo... https://t.co/UljmFQOmfs", 
        "created_at": "2014-07-03T19:21:58Z", 
        "id": "484779098188046336"
    }, 
    {
        "text": "@Cristiano you are my idol.I see your goals everyday.I feel like I am scoring those goals.i ask my friends to call me ronaldo while playing.", 
        "created_at": "2014-07-03T19:23:28Z", 
        "id": "484779475612078081"
    }, 
    {
        "text": "[A Bola] Ronaldo recarrega baterias na Gr\u00e9cia (com v\u00eddeo) http://t.co/yLFq8dVfi8 #desporto", 
        "created_at": "2014-07-03T19:27:33Z", 
        "id": "484780505372442625"
    }, 
    {
        "text": "RT @PedroGoMusic: meu puto Ronaldo, j\u00e1 s\u00e3o 10 aninhos de amizade! Hoje \u00e9 para reinares, mais logo vamos \u00e0s jolas! \u00e9s o maior bff &lt;3 http://\u2026", 
        "created_at": "2014-07-03T19:48:05Z", 
        "id": "484785670758883328"
    }, 
    {
        "text": "@Cristiano Watch me get my air ronaldo:))) belki olur:))", 
        "created_at": "2014-07-03T19:55:27Z", 
        "id": "484787525236846592"
    }, 
    {
        "text": "@Cristiano Ronaldo can you say hello? Im your #1 fan, in from France.", 
        "created_at": "2014-07-03T20:12:26Z", 
        "id": "484791797601030144"
    }, 
    {
        "text": "@Cristiano om ronaldo banguun sauuurrr ..", 
        "created_at": "2014-07-03T20:17:08Z", 
        "id": "484792981346467841"
    }, 
    {
        "text": "@Cristiano Ronaldo y su hermano Hugo! :') http://t.co/V1tRx32QSY", 
        "created_at": "2014-07-03T20:29:05Z", 
        "id": "484795987043827713"
    }, 
    {
        "text": "@Cristiano un ni\u00f1o fue diagnosticado con cancer en los huesos esta en el hospital memorial y su deseo es saludar a Cristiano Ronaldo", 
        "created_at": "2014-07-03T20:31:51Z", 
        "id": "484796685487312896"
    }, 
    {
        "text": "@Cristiano RONALDO EDIT!! Please retweet and favourite if you like it. 10th retweet gets a #shoutout http://t.co/u99rE2I4hn", 
        "created_at": "2014-07-03T20:50:19Z", 
        "id": "484801331006562305"
    }, 
    {
        "text": "@Cristiano viva ronaldo", 
        "created_at": "2014-07-03T20:56:01Z", 
        "id": "484802766783528960"
    }, 
    {
        "text": "@Cristiano @david_alexi Cristiano Ronaldo \ud83d\udc96 please follow me, you will make my life paradise if u do that", 
        "created_at": "2014-07-03T21:13:21Z", 
        "id": "484807129715331072"
    }, 
    {
        "text": "@Cristiano Ronaldo. Well Done!  \u201cYo no intercambio mi camiseta con asesinos\u201d http://t.co/ZhwIG3p6OR", 
        "created_at": "2014-07-03T21:13:29Z", 
        "id": "484807163135938560"
    }, 
    {
        "text": "@Cristiano Cristiano Ronaldo is extremely hot and handsome.", 
        "created_at": "2014-07-03T21:13:58Z", 
        "id": "484807284284211202"
    }, 
    {
        "text": "@Cristiano Ronaldo, que tinha me seguido, por favor", 
        "created_at": "2014-07-03T21:32:40Z", 
        "id": "484811991735750656"
    }, 
    {
        "text": "@Cristiano Ronaldo:')\u2661 http://t.co/KHmgmdsTBP", 
        "created_at": "2014-07-03T21:45:24Z", 
        "id": "484815196134060032"
    }, 
    {
        "text": "percebes tanto disto como o Ronaldo, oh Cinha \ud83d\udca9\ud83d\udca9\ud83d\udca9", 
        "created_at": "2014-07-03T21:45:25Z", 
        "id": "484815197925027840"
    }, 
    {
        "text": "@Cristiano @david_alexi  \u00ce love you ronaldo", 
        "created_at": "2014-07-03T21:47:38Z", 
        "id": "484815754978918400"
    }, 
    {
        "text": "@Cristiano so amazing c Ronaldo", 
        "created_at": "2014-07-03T21:49:35Z", 
        "id": "484816247516061697"
    }, 
    {
        "text": "@Cristiano viva Ronaldo", 
        "created_at": "2014-07-03T21:50:13Z", 
        "id": "484816406887026688"
    }, 
    {
        "text": "@Cristiano Se isso \u00e9 realmente voc\u00ea, por favor responda de volta para mim, ele vai fazer o meu dia. Por favor Ronaldo", 
        "created_at": "2014-07-03T21:52:52Z", 
        "id": "484817074527543296"
    }, 
    {
        "text": "RT @noticiaaominuto: Organiza\u00e7\u00e3o pede a Ronaldo que corte o cabelo http://t.co/lenRFT2uhp #fama", 
        "created_at": "2014-07-03T21:59:10Z", 
        "id": "484818657122713601"
    }, 
    {
        "text": "@Cristiano @david_alexi Hey the one and only Cristiano Ronaldo I know you probaly won't reply but your a REALLY GREAT PERSON", 
        "created_at": "2014-07-03T22:06:49Z", 
        "id": "484820582979338240"
    }, 
    {
        "text": "@zhanqmei ROUBALHEIRA, AINDA \u00c9 PIOR QUE AS MINHAS FOTOS AUTOGRAFADAS DA SUPER POP DO CRISTIANO RONALDO", 
        "created_at": "2014-07-03T22:08:29Z", 
        "id": "484821002506223616"
    }, 
    {
        "text": "Juntos em Mykonos? \u201c@_ptnews: Mykonos TV filma Ronaldo e Mourinho em f\u00e9rias http://t.co/wCgjTJIeme\u201d", 
        "created_at": "2014-07-03T22:13:31Z", 
        "id": "484822269802594304"
    }, 
    {
        "text": "#criseBES RT @rpOliveira: Juntos em Mykonos? \u201c@_ptnews: Mykonos TV filma Ronaldo e Mourinho em f\u00e9rias http://t.co/JBpaMRlUtC\u201d", 
        "created_at": "2014-07-03T22:14:33Z", 
        "id": "484822529186725888"
    }, 
    {
        "text": "@Cristiano @david_alexi And in still having a hard time getting over it Cristiano Ronaldo Your a REALLY GREAT PERSON", 
        "created_at": "2014-07-03T22:15:46Z", 
        "id": "484822838436560896"
    }, 
    {
        "text": "Neymar humilla a cristiano ronaldo y mira como se entran a golpes..!! - http://t.co/hWhC1m8nUF", 
        "created_at": "2014-07-03T22:17:57Z", 
        "id": "484823386863177728"
    }, 
    {
        "text": "Vai l\u00e1, vai. RT @JornalNoticias Mykonos TV filma Ronaldo e Mourinho em f\u00e9rias http://t.co/gkbBqe1XYP", 
        "created_at": "2014-07-03T22:20:43Z", 
        "id": "484824080848547840"
    }, 
    {
        "text": "@Bern_L pelo menos n\u00e3o \u00e9 como quando foi o Ronaldo, jogamos primeiro e levaram-no depois\u2026quase de borla!", 
        "created_at": "2014-07-03T22:32:44Z", 
        "id": "484827106917228545"
    }, 
    {
        "text": "Mykonos TV filma Ronaldo e Mourinho em f\u00e9rias http://t.co/keENME85Vr Ler http://t.co/Hj6M4l00Pn", 
        "created_at": "2014-07-03T22:36:15Z", 
        "id": "484827991176802304"
    }, 
    {
        "text": "[Noticias ao Minuto] Organiza\u00e7\u00e3o pede a Ronaldo que corte o cabelo http://t.co/imLGucThYL", 
        "created_at": "2014-07-03T22:41:47Z", 
        "id": "484829382330949632"
    }, 
    {
        "text": "@Cristiano  hello ,  cristiano ronaldo", 
        "created_at": "2014-07-03T22:42:41Z", 
        "id": "484829612523134976"
    }, 
    {
        "text": "o Ronaldo bem que me podia ter levado de f\u00e9rias com ele para Mykonos", 
        "created_at": "2014-07-03T22:44:59Z", 
        "id": "484830190376591360"
    }, 
    {
        "text": "uma vez o ferrari do Cristiano Ronaldo passou pelo nosso carro quando \u00edamos a caminho do Algarve, JURO.", 
        "created_at": "2014-07-03T22:51:58Z", 
        "id": "484831945944469504"
    }, 
    {
        "text": "RT @riannaperez7: \u201c@Cool_Tweetsss: Cristiano Ronaldo and David Beckham \ud83d\ude0d\ud83d\ude0d\ud83d\ude4c http://t.co/PngZhXF3qY\u201d hottest soccer players ever \ud83d\ude0d", 
        "created_at": "2014-07-03T22:54:19Z", 
        "id": "484832537626550272"
    }, 
    {
        "text": "@rcb80 do Ronaldo n\u00e9? Mesmo cm o joelho fod*** ainda marcou.", 
        "created_at": "2014-07-03T22:58:14Z", 
        "id": "484833523002802176"
    }, 
    {
        "text": "RT @TopWinGames: WINNER of the Team Shirt signed by CRISTIANO RONALDO: Mr Kahled from Egypt! Keep playing on http://t.co/NdEVWnz2RP http://\u2026", 
        "created_at": "2014-07-03T23:02:23Z", 
        "id": "484834569167060993"
    }, 
    {
        "text": "RT @Cristiano: Great day shooting Rankin x Ronaldo for #CR7Underwear with @rankinphoto. Can't wait to show you the new collection! http://t\u2026", 
        "created_at": "2014-07-03T23:04:58Z", 
        "id": "484835217082175488"
    }, 
    {
        "text": "RT @Cristiano: A round of applause to International FC @IFC_FIVES for winning Round One of The GAME by Ronaldo. Congrats guys! http://t.co/\u2026", 
        "created_at": "2014-07-03T23:05:18Z", 
        "id": "484835303371603971"
    }, 
    {
        "text": "@Cristiano. Hey Ronaldo I am a big Real Madrid fan!! You're my role model !  Best of luck in the future! -Evan", 
        "created_at": "2014-07-03T23:10:38Z", 
        "id": "484836644168933376"
    }, 
    {
        "text": "@Cristiano Voc\u00ea Mtoadh O Ronaldo", 
        "created_at": "2014-07-03T23:10:56Z", 
        "id": "484836718156468224"
    }, 
    {
        "text": "O orgulho de ver o @TheRealRyanHiga a mencionar Portugal! Okay que era por causa do Ronaldo...mas mesmo assim ainda conta!", 
        "created_at": "2014-07-03T23:11:45Z", 
        "id": "484836923299856384"
    }, 
    {
        "text": "RT @Cool_Tweetsss: Cristiano Ronaldo and David Beckham \ud83d\ude0d\ud83d\ude0d\ud83d\ude4c http://t.co/AmfujhZrzb", 
        "created_at": "2014-07-03T23:13:41Z", 
        "id": "484837410141118465"
    }, 
    {
        "text": "RT @nuteIla: Cristiano Ronaldo and David Beckham \ud83d\ude0d\ud83d\ude0d\ud83d\ude4c http://t.co/6ZJN55c7d6", 
        "created_at": "2014-07-03T23:13:54Z", 
        "id": "484837465715671041"
    }, 
    {
        "text": "@Cristiano \u2764\u2764\u2764 #CristianoRonaldo #Ronaldo http://t.co/YCtlMeLi3T", 
        "created_at": "2014-07-03T23:17:20Z", 
        "id": "484838330031276032"
    }, 
    {
        "text": "@cristiano New hairstyle  ---------------------------------- #CristianoRonaldo #Cristiano #Ronaldo\u2026 http://t.co/FVdxPCPc58", 
        "created_at": "2014-07-03T23:28:49Z", 
        "id": "484841220859244546"
    }, 
    {
        "text": "@Cristiano  :D S\u00fcpersin ronaldo :D ag\u0131w\u00f6dispw\u00f6dsipwnd http://t.co/JmWbG9qCuZ", 
        "created_at": "2014-07-03T23:41:20Z", 
        "id": "484844371326828545"
    }
]